{
  "fetched_at": "2026-07-04T08:22:50Z",
  "source": "Yahoo/AlJazeera/NBC consensus",
  "urls": [
    "https://sports.yahoo.com/soccer/live/world-cup-2026-bracket-scores-results-schedule-live-updates-round-of-32-173000083.html",
    "https://www.aljazeera.com/sports/liveblog/2026/7/3/live-argentina-vs-cape-verde-fifa-world-cup-2026",
    "https://www.nbcsports.com/soccer/live/argentina-vs-cape-verde-live-updates-score-goals-highlights-stats-2026-fifa-world-cup-july-3"
  ],
  "method": "manual",
  "results": [
    {
      "match_id": "M086",
      "home_goals": 3,
      "away_goals": 2,
      "note": "AET. AlJazeera/NBC: Argentina 3-2 Cape Verde, winner via Borges OG 111"
    },
    {
      "match_id": "M087",
      "home_goals": 1,
      "away_goals": 0,
      "note": "Yahoo: Colombia tops Ghana 1-0 (Arias 14)"
    },
    {
      "match_id": "M088",
      "home_goals": 1,
      "away_goals": 1,
      "penalties": [
        2,
        4
      ],
      "note": "Yahoo: Egypt 1-1 Australia, Egypt advances 4-2 on PKs (Ashour opener, Hany OG equaliser)"
    }
  ]
}
